{"delo": {"name": "Право-троцкистский блок (списки осужденных)", "num": "9-Л/8-4"}, "pages": [{"image": "v04/17-171-412-086.jpg"}, {"image": "v04/17-171-412-087.jpg"}], "sublists": [{"title": "Украинская ССР", "persons": [{"num": "1", "name": "БУКШПАН Михаил Маркович"}, {"num": "2", "name": "ГРИНЕВ Михаил Иосифович"}, {"num": "3", "name": "ГУРОВИЧ Арнольд Павлович"}, {"num": "4", "name": "КАЗБЕК-КАПЛАН Иосиф Яковлевич"}, {"num": "5", "name": "ЛАВРОВ-ШНЕЙДЕР Александр Самойлович"}, {"num": "6", "name": "ОКРУЙ Владимир Иванович"}, {"num": "7", "name": "ТАНТЛЕВСКИЙ Роман Борисович"}, {"num": "8", "name": "ЧАРНЫЙ Пинхус Эльконович"}]}]}