{"title": "РГАСПИ, ф.17, оп.171, дело 9-Л/8-1", "delo": {"name": "Право-троцкистский блок (списки)", "num": "9-Л/8-1"}, "pages": [{"image": "v01/17-171-409-030.jpg"}, {"image": "v01/17-171-409-031.jpg"}, {"image": "v01/17-171-409-032.jpg"}, {"image": "v01/17-171-409-033.jpg"}, {"image": "v01/17-171-409-034.jpg"}, {"image": "v01/17-171-409-035.jpg"}, {"image": "v01/17-171-409-036.jpg"}, {"image": "v01/17-171-409-037.jpg"}, {"image": "v01/17-171-409-038.jpg"}, {"image": "v01/17-171-409-039.jpg"}], "sublists": [{"title": "Список от 19 марта 1937 г. [Свердловская область]", "sublisttitle": "Свердловская область", "pages": [{"page": {"pageid": "31", "tom": "1", "pageintom": "31", "alistid": "4", "pagekind": "1", "arowcount": "24", "picturefile": "17-171-409-031.jpg", "textfile": "", "sublisttitle": "1", "categorytitle": "1", "grouptitle": "0", "podpnkvd": "0", "pometa": "0"}, "page_image": "v01/17-171-409-031.jpg", "persons": [{"num": "1", "name": "АБАЗАПУЛЛО Евгений Павлович"}, {"num": "2", "name": "АБРАМОВ Александр Федорович"}, {"num": "3", "name": "АБРАМОВ Яков Константинович"}, {"num": "4", "name": "АГАФОНОВ Василий Александрович"}, {"num": "5", "name": "АЛЕКСИН Борис Константинович"}, {"num": "6", "name": "АРИСТОВ Алексей Иванович"}, {"num": "7", "name": "БАБЕНКО Сергей Александрович"}, {"num": "8", "name": "БАЛЛЕН Виктор Николаевич"}, {"num": "9", "name": "БАРКОВСКИЙ Павел Васильевич"}, {"num": "10", "name": "БЕЛЯЕВ Матвей Александрович"}, {"num": "11", "name": "БЕЛЬТЮКОВ Петр Сисипатович"}, {"num": "12", "name": "БОБЫЛЕВ Николай Александрович"}, {"num": "13", "name": "БОГДАНОВ Евстафий Сергеевич"}, {"num": "14", "name": "БОНДАРЕНКО Степан Маркович"}, {"num": "15", "name": "БЕРДЫШЕВ Федор Яковлевич"}, {"num": "16", "name": "БУРЛАКОВ Иван Иванович"}, {"num": "17", "name": "БУРОВ Михаил Васильевич"}, {"num": "18", "name": "БУРЯ Николай Никитич"}, {"num": "19", "name": "ВЕВИОРОВСКИЙ Александр Федорович"}, {"num": "20", "name": "ВОРОТНИКОВ Михаил Васильевич"}, {"num": "21", "name": "ГАЙДУКОВ Василий Иванович"}, {"num": "22", "name": "ГАЙДЕРОВ Федор Васильевич"}, {"num": "23", "name": "ГАЛЬПЕРИН Александр Израилевич"}, {"num": "24", "name": "ГИНГОРН Семен Владимирович"}]}, {"page": {"pageid": "32", "tom": "1", "pageintom": "32", "alistid": "4", "pagekind": "1", "arowcount": "26", "picturefile": "17-171-409-032.jpg", "textfile": "", "sublisttitle": "0", "categorytitle": "0", "grouptitle": "0", "podpnkvd": "0", "pometa": "0"}, "page_image": "v01/17-171-409-032.jpg", "persons": [{"num": "25", "name": "ГИНЗБУРГ Лев Ефимович"}, {"num": "26", "name": "ГОЛОВИН Василий Федорович"}, {"num": "27", "name": "ГОРОХОВ Василий Лаврентьевич"}, {"num": "28", "name": "ГУРИН Пимен Федорович"}, {"num": "29", "name": "ДАЙБОВ Петр Степанович"}, {"num": "30", "name": "ДАНИЛОВ Иван Афанасьевич"}, {"num": "31", "name": "ДЕМИН Федор Семенович"}, {"num": "32", "name": "ДОЛМАТОВ Яков Яковлевич"}, {"num": "33", "name": "ДОРОФЕЕВ Михаил Федорович"}, {"num": "34", "name": "ДРОБОВИЧ Владислав Антонович"}, {"num": "35", "name": "ДЫКМАН Зельман Айзикович"}, {"num": "36", "name": "ДЬЯЧКОВ Михаил Николаевич"}, {"num": "37", "name": "ЕЛЬКОВИЧ Яков Рафаилович"}, {"num": "38", "name": "ЕМЕЛЬЯНОВ Владимир Павлович"}, {"num": "39", "name": "ЖАРИКОВ Митрофан Архипович"}, {"num": "40", "name": "ЗАГАРСКИХ Алексей Георгиевич"}, {"num": "41", "name": "ЗАГВОЗДКИН Иван Степанович"}, {"num": "42", "name": "ЗАЙЦЕВ Евстигней Алексеевич"}, {"num": "43", "name": "ЗАКУСИН Павел Иосифович"}, {"num": "44", "name": "ЗВОНАРЕВ Василий Николаевич"}, {"num": "45", "name": "ИНЮТИН Александр Петрович"}, {"num": "46", "name": "КАЗАНЦЕВ Борис Александрович"}, {"num": "47", "name": "КАРМАННИКОВ Михаил Васильевич"}, {"num": "48", "name": "КЛЕПАЦКИЙ Степан Иванович"}, {"num": "49", "name": "КОЖЕВНИКОВ Иван Федорович"}, {"num": "50", "name": "КОЗИН Иван Алексеевич"}]}, {"page": {"pageid": "33", "tom": "1", "pageintom": "33", "alistid": "4", "pagekind": "1", "arowcount": "26", "picturefile": "17-171-409-033.jpg", "textfile": "", "sublisttitle": "0", "categorytitle": "0", "grouptitle": "0", "podpnkvd": "0", "pometa": "0"}, "page_image": "v01/17-171-409-033.jpg", "persons": [{"num": "51", "name": "КОЗЫРЕВ Иван Васильевич"}, {"num": "52", "name": "КОЛЕГАЕВ Андрей Лукич"}, {"num": "53", "name": "КОРОТКИН Израиль Михайлович"}, {"num": "54", "name": "КРИВОНОС Сергей Лукич"}, {"num": "55", "name": "КРОПОТОВ Иван Терентьевич"}, {"num": "56", "name": "КУЛИКОВ Василий Яковлевич"}, {"num": "57", "name": "КУРОЧКИН Иван Иванович"}, {"num": "58", "name": "ЛЕОНТЬЕВ Яков Иванович"}, {"num": "59", "name": "ЛЫСКОВ Михаил Иванович"}, {"num": "60", "name": "МАРЬЯСИН Лазарь Миронович"}, {"num": "61", "name": "МАЦ Борис Григорьевич"}, {"num": "62", "name": "МЕЙЕРСОН Владимир Матвеевич"}, {"num": "63", "name": "МЕДНИКОВ Николай Иванович"}, {"num": "64", "name": "МИХЕТКО Николай Прокопьевич"}, {"num": "65", "name": "МОИСЕЕВ Семен Степанович"}, {"num": "66", "name": "МРАЧКОВСКИЙ Леонид Витальевич"}, {"num": "67", "name": "МРАЧКОВСКИЙ Николай Витальевич"}, {"num": "68", "name": "МЯГКОВ Степан Ефимович"}, {"num": "69", "name": "НИКОЛАЕВ Константин Петрович"}, {"num": "70", "name": "ОЛЬХОВ Василий Максимович"}, {"num": "71", "name": "ОЛЬХОВСКИЙ Николай Григорьевич"}, {"num": "72", "name": "ПЕРРО Владислав Станиславович"}, {"num": "73", "name": "ПИЩАЛЬНИКОВ Константин Михайлович"}, {"num": "74", "name": "ПОЛЯКОВ Николай Иванович"}, {"num": "75", "name": "ПУЗЫРЕВ Михаил Иванович"}, {"num": "76", "name": "ПРОСКУРЯКОВ Павел Матвеевич"}]}, {"page": {"pageid": "34", "tom": "1", "pageintom": "34", "alistid": "4", "pagekind": "1", "arowcount": "27", "picturefile": "17-171-409-034.jpg", "textfile": "", "sublisttitle": "0", "categorytitle": "0", "grouptitle": "0", "podpnkvd": "0", "pometa": "0"}, "page_image": "v01/17-171-409-034.jpg", "persons": [{"num": "77", "name": "ПУЧКОВ Василий Иванович"}, {"num": "78", "name": "РАВИНСКИЙ Борис Алексеевич"}, {"num": "79", "name": "РАСТОШИНСКИЙ Сергей Митрофанович"}, {"num": "80", "name": "РОМАНОВ Николай Михайлович"}, {"num": "81", "name": "СВЕШНИКОВ Василий Иванович"}, {"num": "82", "name": "СЕРЫХ Николай Венедиктович"}, {"num": "83", "name": "СКРИПОВ Алексей Александрович"}, {"num": "84", "name": "СЛОБОДЧИКОВ Петр Александрович"}, {"num": "85", "name": "СЛОЕВСКИЙ Константин Антонович"}, {"num": "86", "name": "СТЕПАНОВ Александр Николаевич"}, {"num": "87", "name": "СТРИГАНОВ Федор Игнатьевич"}, {"num": "88", "name": "СУХОРУКОВ Степан Васильевич"}, {"num": "89", "name": "СЫТНИК Аркадий Ефимович"}, {"num": "90", "name": "СЫЧЕВ Николай Сергеевич"}, {"num": "91", "name": "ТАУБЕ Николай Николаевич"}, {"num": "92", "name": "ТОНКОВ Александр Владимирович"}, {"num": "93", "name": "ТРУБИЕВ Николай Иванович"}, {"num": "94", "name": "УПОРОВ Александр Васильевич"}, {"num": "95", "name": "ФЕДОСЕЕВ Василий Семенович"}, {"num": "96", "name": "ФИЛАТОВ Павел Федорович"}, {"num": "97", "name": "ФИЛИППОВИЧ Иосиф Константинович"}, {"num": "98", "name": "ФИНКЕЛЬШТЕЙН Натан Григорьевич"}, {"num": "99", "name": "ФРОЛОВ Григорий Александрович"}, {"num": "100", "name": "ЧЕРНЕЦОВ Петр Николаевич"}, {"num": "101", "name": "ЧЕРНУШКИН Анатолий Владимирович"}, {"num": "102", "name": "ЧУБАТКИН Иван Васильевич"}, {"num": "103", "name": "ЧУКИЧЕВ Трофим Евсеевич"}]}, {"page": {"pageid": "35", "tom": "1", "pageintom": "35", "alistid": "4", "pagekind": "1", "arowcount": "8", "picturefile": "17-171-409-035.jpg", "textfile": "", "sublisttitle": "0", "categorytitle": "0", "grouptitle": "0", "podpnkvd": "1", "pometa": "0"}, "page_image": "v01/17-171-409-035.jpg", "persons": [{"num": "104", "name": "ШЕРШНЕВ Матвей Андреевич"}, {"num": "105", "name": "ШЕРШНЕВ Михаил Иванович"}, {"num": "106", "name": "ШУЛИКИН Иван Петрович"}, {"num": "107", "name": "ЮДАНОВ Андрей Яковлевич"}, {"num": "108", "name": "ЮЛИН Александр Иванович"}, {"num": "109", "name": "ЮХНО Александр Прохорович"}, {"num": "110", "name": "ЮШКИН Петр Сергеевич"}, {"num": "111", "name": "ЯЗОВСКИХ Александр Кузьмич"}]}, {"page": {"pageid": "36", "tom": "1", "pageintom": "36", "alistid": "4", "pagekind": "1", "arowcount": "25", "picturefile": "17-171-409-036.jpg", "textfile": "", "sublisttitle": "1", "categorytitle": "1", "grouptitle": "0", "podpnkvd": "0", "pometa": "0"}, "page_image": "v01/17-171-409-036.jpg", "persons": [{"num": "1", "name": "АРТЕМЬЕВ Иван Александрович"}, {"num": "2", "name": "БАЛЬЧУНАС Иван Михайлович"}, {"num": "3", "name": "БОРИСОВ Михаил Иванович"}, {"num": "4", "name": "БУШУЕВ Николай Иванович"}, {"num": "5", "name": "ВОРОПАЕВ Сергей Петрович"}, {"num": "6", "name": "ВЕТРОВ Виктор Федорович"}, {"num": "7", "name": "ВИНОГРАДОВ Александр Николаевич"}, {"num": "8", "name": "ВОРОБЬЕВ Ефим Степанович"}, {"num": "9", "name": "ГИНЗБУРГ Илья Наумович"}, {"num": "10", "name": "ГЛОТОВ Андрей Артемьевич"}, {"num": "11", "name": "ГОНЧАРОВ Иван Алексеевич"}, {"num": "12", "name": "ГРЕБНЕВ (ГРЕБЕНЕВ) Константин Всеволодович"}, {"num": "13", "name": "ГРИГОРЬЕВ Василий Николаевич"}, {"num": "14", "name": "ГРОЗНЫХ Александр Михайлович"}, {"num": "15", "name": "ГРОЗНЫХ Василий Афанасьевич"}, {"num": "16", "name": "ГРУБЕР Иосиф Яковлевич"}, {"num": "17", "name": "ЕЛИСЕЕВ Иван Иванович"}, {"num": "18", "name": "ЖАРИКОВ Василий Корнилович"}, {"num": "19", "name": "ЖЕРЛИЦИН Виктор Сергеевич"}, {"num": "20", "name": "ЗАЙЦЕВ Виктор Васильевич"}, {"num": "21", "name": "ЗАЛИВИН Федор Александрович"}, {"num": "22", "name": "ЗАХАРОВ Михаил Павлович"}, {"num": "23", "name": "ИВАНОВ Григорий Федорович"}, {"num": "24", "name": "ИЦКОВСКИЙ Евгений(Рувим) Львович"}, {"num": "25", "name": "КОГАН Иосиф Соломонович"}]}, {"page": {"pageid": "37", "tom": "1", "pageintom": "37", "alistid": "4", "pagekind": "1", "arowcount": "26", "picturefile": "17-171-409-037.jpg", "textfile": "", "sublisttitle": "0", "categorytitle": "0", "grouptitle": "0", "podpnkvd": "0", "pometa": "0"}, "page_image": "v01/17-171-409-037.jpg", "persons": [{"num": "26", "name": "КОЗЕЛЕВ Борис Григорьевич"}, {"num": "27", "name": "КОРОСТЕЛЕВ Александр Никандрович"}, {"num": "28", "name": "КУЗЬМИН Виктор Иванович"}, {"num": "29", "name": "ЛАПШИН Афанасий Ильич"}, {"num": "30", "name": "ЛЕКОМЦЕВ Андрей Васильевич"}, {"num": "31", "name": "ЛИПЛАВСКИЙ Иосиф Леонтьевич"}, {"num": "32", "name": "ЛИСЯКИН Василий Васильевич"}, {"num": "33", "name": "МАЛЬЦЕВ Иван Михайлович"}, {"num": "34", "name": "МАРЬЯНОВ Иван Степанович"}, {"num": "35", "name": "МАТВЕЕВ Евстафий Георгиевич"}, {"num": "36", "name": "МАХНУТИН Аркадий Михайлович"}, {"num": "37", "name": "МЕДВЕДЕВ Иосиф Григорьевич"}, {"num": "38", "name": "МИТРОПОЛЬСКИЙ Александр Петрович"}, {"num": "39", "name": "МОЛОСТОВ Иван Степанович"}, {"num": "40", "name": "МОРГУНОВ Борис Николаевич"}, {"num": "41", "name": "МРАЧКОВСКИЙ Вячеслав Леонидович"}, {"num": "42", "name": "МРАЧКОВСКИЙ Евгений Леонидович"}, {"num": "43", "name": "МУРТАЗИН Сафа Юсуфович"}, {"num": "44", "name": "НЕПУТИН Иван Иванович"}, {"num": "45", "name": "ПЕРЦЕВ Иван Емельянович"}, {"num": "46", "name": "ПЕРЦЕВ Петр Емельянович"}, {"num": "47", "name": "ПЕРШАКОВ Иван Трофимович"}, {"num": "48", "name": "ПОМОРЦЕВ Михаил Яковлевич"}, {"num": "49", "name": "РЕПИН Михаил Алексеевич"}, {"num": "50", "name": "РУДЕНКО Александр Николаевич"}, {"num": "51", "name": "РУЗДАН Георгий Николаевич"}]}, {"page": {"pageid": "38", "tom": "1", "pageintom": "38", "alistid": "4", "pagekind": "1", "arowcount": "22", "picturefile": "17-171-409-038.jpg", "textfile": "", "sublisttitle": "0", "categorytitle": "0", "grouptitle": "0", "podpnkvd": "1", "pometa": "0"}, "page_image": "v01/17-171-409-038.jpg", "persons": [{"num": "52", "name": "САВЕЛЬЕВ Василий Андреевич"}, {"num": "53", "name": "САННИКОВ Евгений Степанович"}, {"num": "54", "name": "СИДНЕВ Михаил Васильевич"}, {"num": "55", "name": "СИПИЦЫН Петр Федорович"}, {"num": "56", "name": "СКРЯБИН Михаил Дмитриевич"}, {"num": "57", "name": "СЛЕЗКИН Василий Григорьевич"}, {"num": "58", "name": "СМОЛЬНИКОВА Елена Александровна"}, {"num": "59", "name": "СОМИНИЧ Юрий Васильевич"}, {"num": "60", "name": "СТЕПАНОВ Владимир Васильевич"}, {"num": "61", "name": "СУВОРОВ Виктор Михайлович"}, {"num": "62", "name": "СЫСОЕВ Василий Павлович"}, {"num": "63", "name": "УФИМЦЕВА Мария Николаевна"}, {"num": "64", "name": "УШАКОВ Иван Павлович"}, {"num": "65", "name": "ФЕДОРУК Алексей Михайлович"}, {"num": "66", "name": "ФЕДОТОВ Павел Михайлович"}, {"num": "67", "name": "ЧАЩИН Константин Егорович"}, {"num": "68", "name": "ЧЕРЕПАНОВ Георгий Александрович"}, {"num": "69", "name": "ШАМАРИН Илья Андреевич"}, {"num": "70", "name": "ШВЕЦОВ Михаил Ильич"}, {"num": "71", "name": "ШИМКОВИЧ Иван Алексеевич"}, {"num": "72", "name": "ШТИШЕВСКИЙ Игорь Владимирович"}, {"num": "73", "name": "ЮРОВСКИХ Григорий Васильевич"}]}, {"page": {"pageid": "39", "tom": "1", "pageintom": "39", "alistid": "4", "pagekind": "1", "arowcount": "13", "picturefile": "17-171-409-039.jpg", "textfile": "", "sublisttitle": "1", "categorytitle": "1", "grouptitle": "0", "podpnkvd": "1", "pometa": "0"}, "page_image": "v01/17-171-409-039.jpg", "persons": [{"num": "1", "name": "АЛДОНОВ Николай Иванович"}, {"num": "2", "name": "ВДОВИН Михаил Васильевич"}, {"num": "3", "name": "ДАВЫДОВ Николай Иванович"}, {"num": "4", "name": "ЗВЕРЕВА Августа Ивановна"}, {"num": "5", "name": "КАЙГОРОДОВ Александр Степанович"}, {"num": "6", "name": "КОНДАКОВ Василий Ильич"}, {"num": "7", "name": "ЛАРЬКОВ Петр Константинович"}, {"num": "8", "name": "МОРОЗОВ Михаил Михайлович"}, {"num": "9", "name": "МРАЧКОВСКИЙ Виталий Леонидович"}, {"num": "10", "name": "ПИСАРЕВ Георгий Модестович"}, {"num": "11", "name": "РУДНЕВСКИЙ Николай Яковлевич"}, {"num": "12", "name": "СЕРГЕЕВ Федор Константинович"}, {"num": "13", "name": "ТРУБАНОВСКИЙ Илья Васильевич"}]}]}]}