{"title": "РГАСПИ, ф.17, оп.171, дело 9-Л/8-5", "delo": {"name": "Право-троцкистский блок (списки осужденных)", "num": "9-Л/8-5"}, "pages": [{"image": "v05/17-171-413-301.jpg"}, {"image": "v05/17-171-413-302.jpg"}, {"image": "v05/17-171-413-303.jpg"}, {"image": "v05/17-171-413-304.jpg"}, {"image": "v05/17-171-413-305.jpg"}, {"image": "v05/17-171-413-306.jpg"}, {"image": "v05/17-171-413-307.jpg"}, {"image": "v05/17-171-413-308.jpg"}, {"image": "v05/17-171-413-309.jpg"}, {"image": "v05/17-171-413-310.jpg"}], "sublists": [{"title": "Список от 22 декабря 1937г. [Оренбургская область]", "sublisttitle": "Оренбургская область", "pages": [{"page": {"pageid": "1427", "tom": "5", "pageintom": "303", "alistid": "142", "pagekind": "1", "arowcount": "24", "picturefile": "17-171-413-303.jpg", "textfile": "", "sublisttitle": "1", "categorytitle": "1", "grouptitle": "0", "podpnkvd": "0", "pometa": "0"}, "page_image": "v05/17-171-413-303.jpg", "persons": [{"num": "1", "name": "АБДУЖАБАРОВ Юсуп"}, {"num": "2", "name": "АЛЕКСАНДРОВИЧ Михаил Яковлевич"}, {"num": "3", "name": "АНДРИАНОВ Борис Васильевич"}, {"num": "4", "name": "АНДРИАНОВА Вера Александровна"}, {"num": "5", "name": "АНТОНЕВИЧ Владислав Феликсович"}, {"num": "6", "name": "АРТЕМЬЕВ Дмитрий Федорович"}, {"num": "7", "name": "АРТЮШИХИН Александр Михайлович"}, {"num": "8", "name": "АХМЕТОВ Батрахан Рахимович"}, {"num": "9", "name": "БАЗЕНАУ Оскар Карлович"}, {"num": "10", "name": "БАРАБАНОВ Павел Николаевич"}, {"num": "11", "name": "БАСОВ Иван Яковлевич"}, {"num": "12", "name": "БЕЛКИН Кронид Константинович"}, {"num": "13", "name": "БЕЛОВ Василий Иванович"}, {"num": "14", "name": "БЕЛОВ Николай Владимирович"}, {"num": "15", "name": "БЕЛУХИН Тимофей Яковлевич"}, {"num": "16", "name": "БЕЛЯКОВ Алексей Иванович"}, {"num": "17", "name": "БЕРКУТОВ-ШАНДОР Николай Михайлович"}, {"num": "18", "name": "БИСЬКО Михаил Игнатьевич"}, {"num": "19", "name": "БОРОВИК Илларион Семенович"}, {"num": "20", "name": "БОРОДИН Иван Алексеевич"}, {"num": "21", "name": "БУРАКОВ Василий Григорьевич"}, {"num": "22", "name": "БЫКОВ Фрол Иванович"}, {"num": "23", "name": "ВАВИЛКИН Василий Николаевич"}, {"num": "24", "name": "ВАГАНОВ Михаил Ефимович"}]}, {"page": {"pageid": "1428", "tom": "5", "pageintom": "304", "alistid": "142", "pagekind": "1", "arowcount": "30", "picturefile": "17-171-413-304.jpg", "textfile": "", "sublisttitle": "0", "categorytitle": "0", "grouptitle": "0", "podpnkvd": "0", "pometa": "0"}, "page_image": "v05/17-171-413-304.jpg", "persons": [{"num": "25", "name": "ВАКУЛЕНКО Михаил Михайлович"}, {"num": "26", "name": "ВЕГЕНЕР Валентин Николаевич"}, {"num": "27", "name": "ВЕРИГО Николай Иосифович"}, {"num": "28", "name": "ВИДОНОВ Александр Васильевич"}, {"num": "29", "name": "ВОДОПЬЯНОВ Алексей Федорович"}, {"num": "30", "name": "ВОЛК-ЛЕВАНОВИЧ Иосиф Васильевич"}, {"num": "31", "name": "ВОЛОДИН-БОЛОТОВ Сергей Андрианович"}, {"num": "32", "name": "ВОЛЫНКИН Иван Федорович"}, {"num": "33", "name": "ГАРДЕР Герман Юльевич"}, {"num": "34", "name": "ГЕОРГИУ Александр Александрович"}, {"num": "35", "name": "ГЕРАСИМОВ Федор Алексеевич"}, {"num": "36", "name": "ГОЛДОБИН Семен Алексеевич"}, {"num": "37", "name": "ГОРЕНШТЕЙН Михаил Иосифович"}, {"num": "38", "name": "ГРАБОВСКИЙ Петр Адольфович"}, {"num": "39", "name": "ГРИНКЕВИЧ Анатолий Матвеевич"}, {"num": "40", "name": "ГУЗЕНКО Илья Павлович"}, {"num": "41", "name": "ГУСЕВ Александр Дмитриевич"}, {"num": "42", "name": "ГУСЕВ Михаил Ильич"}, {"num": "43", "name": "ГУЩИН Евдоким Дмитриевич"}, {"num": "44", "name": "ДЕМЕНТЬЕВ Константин Константинович"}, {"num": "45", "name": "ДЕНИСОВ Александр Васильевич"}, {"num": "46", "name": "ДИВЕЕВ Владимир Семенович"}, {"num": "47", "name": "ДОГМАРОВ-ИВАНОВ Николай Владимирович"}, {"num": "48", "name": "ДУКС Вольдемар-Генрих-Курт Павлович"}, {"num": "49", "name": "ДЫМОВ-СКОРОДУМОВ Дмитрий Владимирович"}, {"num": "50", "name": "ЕВДОКИМОВ Михаил Иванович"}, {"num": "51", "name": "ЕВИН Иван Павлович"}, {"num": "52", "name": "ЕЛИСЕЕВ Сергей Георгиевич"}, {"num": "53", "name": "ЕПИФАНЦЕВ Федор Тимофеевич"}, {"num": "54", "name": "ЗАХАРОВ Михаил Ильич"}]}, {"page": {"pageid": "1429", "tom": "5", "pageintom": "305", "alistid": "142", "pagekind": "1", "arowcount": "29", "picturefile": "17-171-413-305.jpg", "textfile": "", "sublisttitle": "0", "categorytitle": "0", "grouptitle": "0", "podpnkvd": "0", "pometa": "0"}, "page_image": "v05/17-171-413-305.jpg", "persons": [{"num": "55", "name": "ЗИНОВЬЕВ Петр Федорович"}, {"num": "56", "name": "ЗЛАТИН Лев Полтиэлевич"}, {"num": "57", "name": "ИВАНОВ Александр Дмитриевич"}, {"num": "58", "name": "КАМИНСКИЙ Эдуард Альбертович"}, {"num": "59", "name": "КАРТАШЕВ Андрей Михайлович"}, {"num": "60", "name": "КЕРЕНСКАЯ Елена Федоровна"}, {"num": "61", "name": "КИРШ Василий Рейнгольдович"}, {"num": "62", "name": "КИССЕЛЬ-ШРЕЙДЕР Нина Станиславовна"}, {"num": "63", "name": "КЛИМЕЦКИЙ Георгий Владиславович"}, {"num": "64", "name": "КНОХ Азриэль Давыдович"}, {"num": "65", "name": "КОВАЛЕНКО Константин Иванович"}, {"num": "66", "name": "КОВАЛЬЧУК Александр Михайлович"}, {"num": "67", "name": "КОЗИЧ Гордей Данилович"}, {"num": "68", "name": "КОЗЛОВ Алексей Егорович"}, {"num": "69", "name": "КОНДРАТЬЕВ Михаил Павлович"}, {"num": "70", "name": "КОНОГОВ Петр Иванович"}, {"num": "71", "name": "КОНСТАНТИНОВ Николай Иванович"}, {"num": "72", "name": "КОПЫТИН Петр Федорович"}, {"num": "73", "name": "КОРОЛЕВ Георгий Петрович"}, {"num": "74", "name": "КОРОСТЕЛЕВ Анатолий Степанович"}, {"num": "75", "name": "КОСОВ Иван Никитович"}, {"num": "76", "name": "КОТЕЛЬНИКОВ Дмитрий Гурьевич"}, {"num": "77", "name": "КОТОВ Павел Иванович"}, {"num": "78", "name": "КОШЕВАЦКИЙ Михаил Алексеевич"}, {"num": "79", "name": "КОШЕЛЕНКО Кузьма Семенович"}, {"num": "80", "name": "КРАСНОРУЦКИЙ Петр Тихонович"}, {"num": "81", "name": "КРИВЧИК (она же БОГОМОЛОВА-ЛЕОНТЬЕВА) Мария Климентьевна"}, {"num": "82", "name": "КУЛИЧКОВ Василий Иванович"}, {"num": "83", "name": "КУЛЬКОВ Николай Степанович"}]}, {"page": {"pageid": "1430", "tom": "5", "pageintom": "306", "alistid": "142", "pagekind": "1", "arowcount": "29", "picturefile": "17-171-413-306.jpg", "textfile": "", "sublisttitle": "0", "categorytitle": "0", "grouptitle": "0", "podpnkvd": "0", "pometa": "0"}, "page_image": "v05/17-171-413-306.jpg", "persons": [{"num": "84", "name": "КУЛЬКОВ Сергей Алексеевич"}, {"num": "85", "name": "КУРАГИН Георгий Федорович"}, {"num": "86", "name": "КУЧЕРЧАНОВ Анатолий Иванович"}, {"num": "87", "name": "КУЧИН-ОРАНСКИЙ Георгий Дмитриевич"}, {"num": "88", "name": "ЛАТЕНКО Василий Федорович"}, {"num": "89", "name": "ЛИСИН Александр Федорович"}, {"num": "90", "name": "ЛИСОВСКИЙ Ксаверий Иванович"}, {"num": "91", "name": "ЛОБАНОК Клавдий Артемьевич"}, {"num": "92", "name": "ЛОБОВА-БУРЕНИНА Евгения Максимовна"}, {"num": "93", "name": "ЛОРЕР Федор Федорович"}, {"num": "94", "name": "ЛУКША Станислав Иосифович"}, {"num": "95", "name": "ЛУТЦЕВ Сергей Иванович"}, {"num": "96", "name": "ЛЮТИН Владимир Сергеевич"}, {"num": "97", "name": "МАЙБОРОДА Николай Федорович"}, {"num": "98", "name": "МАКАРОВ Леонтий Иванович"}, {"num": "99", "name": "МАКЕЕВ Алексей Митрофанович"}, {"num": "100", "name": "МАКЕЕВ Михаил Иванович"}, {"num": "101", "name": "МАЛИНОВСКИЙ Владимир Сергеевич"}, {"num": "102", "name": "МАМОНОВ Николай Тимофеевич"}, {"num": "103", "name": "МАРКИЗОВ Николай Ксенофонтович"}, {"num": "104", "name": "МАРТЕНС Константин Константинович"}, {"num": "105", "name": "МАРТЫНОВ Александр Федорович"}, {"num": "106", "name": "МАСЛИНСКИЙ Николай Александрович"}, {"num": "107", "name": "МАСЮКОВ Константин Порфирьевич"}, {"num": "108", "name": "МИТРОЩЕНКОВ Петр Дмитриевич"}, {"num": "109", "name": "МУЗАЛЕВСКИЙ Василий Владимирович"}, {"num": "110", "name": "НЕКРАШ Виктор Иосифович"}, {"num": "111", "name": "НИКОНЕНКО Тимофей Афанасьевич"}, {"num": "112", "name": "НОВИЦКИЙ Анатолий Иванович"}]}, {"page": {"pageid": "1431", "tom": "5", "pageintom": "307", "alistid": "142", "pagekind": "1", "arowcount": "29", "picturefile": "17-171-413-307.jpg", "textfile": "", "sublisttitle": "0", "categorytitle": "0", "grouptitle": "0", "podpnkvd": "0", "pometa": "0"}, "page_image": "v05/17-171-413-307.jpg", "persons": [{"num": "113", "name": "НОВИЦКИЙ Антон Корнилович"}, {"num": "114", "name": "НОВИЧКОВ Иван Трофимович"}, {"num": "115", "name": "ОКРУГИН Никифор Иванович"}, {"num": "116", "name": "ОСТРОМЕЦКИЙ Борис Порфирьевич"}, {"num": "117", "name": "ОСИНСКИЙ Александр Степанович"}, {"num": "118", "name": "ПАВЛОВ Сергей Дмитриевич"}, {"num": "119", "name": "ПАВЛОВСКИЙ Бронислав Янович"}, {"num": "120", "name": "ПЕТРОВ-ДАВЫДОВ Иван Константинович"}, {"num": "121", "name": "ПЕТРУК Александр Васильевич"}, {"num": "122", "name": "ПИТЧ Эдуард Августович"}, {"num": "123", "name": "ПОЗНОХИРИН Лука Фалалеевич"}, {"num": "124", "name": "ПОЛЯКОВ Михаил Михайлович"}, {"num": "125", "name": "ПОПОВ Сергей Никифорович"}, {"num": "126", "name": "ПОТАПОВ Александр Емельянович"}, {"num": "127", "name": "ПРИМАК Иосиф Семенович"}, {"num": "128", "name": "РАДИН-ЗИНГЕРАМН Исаак Соломонович"}, {"num": "129", "name": "РЕННИ Владимир Александрович"}, {"num": "130", "name": "РОДИОНОВ Иван Антонович"}, {"num": "131", "name": "РОЗЕНШТЕЙН Михаил Александрович"}, {"num": "132", "name": "РОЛАУ Рейнгольд Яковлевич"}, {"num": "133", "name": "РУДНИЦКИЙ Лев Венедиктович"}, {"num": "134", "name": "РУДЬ Федор Трофимович"}, {"num": "135", "name": "САЛИХОВ Галимзян Саидгареевич"}, {"num": "136", "name": "САПОЛАЕВ Петр Ильич"}, {"num": "137", "name": "СЕДЛЕЦКИЙ Дмитрий Александрович"}, {"num": "138", "name": "СЕДОВ Николай Трофимович"}, {"num": "139", "name": "СЕЛИВЕРСТОВ Геннадий Иванович"}, {"num": "140", "name": "СИДОРОВ Федор Андриянович"}, {"num": "141", "name": "СМОЛА Александр Георгиевич"}]}, {"page": {"pageid": "1432", "tom": "5", "pageintom": "308", "alistid": "142", "pagekind": "1", "arowcount": "28", "picturefile": "17-171-413-308.jpg", "textfile": "", "sublisttitle": "0", "categorytitle": "0", "grouptitle": "0", "podpnkvd": "0", "pometa": "0"}, "page_image": "v05/17-171-413-308.jpg", "persons": [{"num": "142", "name": "СМОЛЕНСКИЙ Филипп Трофимович"}, {"num": "143", "name": "СОЛОДКОВ Михаил Степанович"}, {"num": "144", "name": "СОРОЦКИЙ Виктор Александрович"}, {"num": "145", "name": "СПАССКИЙ Георгий Матвеевич"}, {"num": "146", "name": "СУББОТИН Алексей Васильевич"}, {"num": "147", "name": "СУБОЧ Савва Куприянович"}, {"num": "148", "name": "СУНДУКОВ Михаил Дмитриевич"}, {"num": "149", "name": "ТЕЛЕГИН Владимир Михайлович"}, {"num": "150", "name": "ТЭН Николай Антонович"}, {"num": "151", "name": "ТЮШЕВСКИЙ Иван Федорович"}, {"num": "152", "name": "УМАНСКАЯ Серафима Ефремовна"}, {"num": "153", "name": "ФЕДОРОВИЧ Даниил Андреевич"}, {"num": "154", "name": "ФИЛИППОВ Владимир Петрович"}, {"num": "155", "name": "ФИНКЕЛЬ Арон Адольфович"}, {"num": "156", "name": "ФОЛЬКЕРТ Авенир Адольфович"}, {"num": "157", "name": "ФРЕЙМАН Роберт Христианович"}, {"num": "158", "name": "ХАЗЕЛЬ Всеволод Александрович"}, {"num": "159", "name": "ХОДОКОВСКИЙ Михаил Леонидович"}, {"num": "160", "name": "ЦИХОН Федор Иванович"}, {"num": "161", "name": "ЧАЙКИН Петр Степанович"}, {"num": "162", "name": "ЧЕРНОБРИВЕНКО Иван Васильевич"}, {"num": "163", "name": "ЧЕРНЫШЕВ Сергей Николаевич"}, {"num": "164", "name": "ЧИСТОСЕРДОВ Алексей Петрович"}, {"num": "165", "name": "ШАБАШЕВ Сергей Иосифович"}, {"num": "166", "name": "ШАВРИН Лука Куприянович"}, {"num": "167", "name": "ШАРАПОВ Константин Федорович"}, {"num": "168", "name": "ШЕВЕЛИН Виктор Михайлович"}, {"num": "169", "name": "ШЕПШЕЛЕВИЧ Соломон Иудович"}]}, {"page": {"pageid": "1433", "tom": "5", "pageintom": "309", "alistid": "142", "pagekind": "1", "arowcount": "8", "picturefile": "17-171-413-309.jpg", "textfile": "", "sublisttitle": "0", "categorytitle": "0", "grouptitle": "0", "podpnkvd": "1", "pometa": "0"}, "page_image": "v05/17-171-413-309.jpg", "persons": [{"num": "170", "name": "ШЕПШЕЛЕВИЧ-ФАЙНБЕРГ Елена Абрамовна"}, {"num": "171", "name": "ШЕРВУД Олег Алексеевич"}, {"num": "172", "name": "ШМЫРОВ Александр Федорович"}, {"num": "173", "name": "ШНЕЙДЕР Авраам Исаакович"}, {"num": "174", "name": "ШРЕЙДЕР Владимир Николаевич"}, {"num": "175", "name": "ЮЩИН Георгий Тимофеевич"}, {"num": "176", "name": "ЯЛОВОЙ Григорий Лаврентьевич"}, {"num": "177", "name": "ЯСУТИС Норберт Александрович"}]}, {"page": {"pageid": "1434", "tom": "5", "pageintom": "310", "alistid": "142", "pagekind": "1", "arowcount": "4", "picturefile": "17-171-413-310.jpg", "textfile": "", "sublisttitle": "1", "categorytitle": "1", "grouptitle": "0", "podpnkvd": "1", "pometa": "0"}, "page_image": "v05/17-171-413-310.jpg", "persons": [{"num": "1", "name": "ВОРОНОВ Дмитрий Георгиевич"}, {"num": "2", "name": "ГАНЮШКИН Сергей Моисеевич"}, {"num": "3", "name": "ГОРЬКОВ Павел Васильевич"}, {"num": "4", "name": "ЛИТВИНОВ Георгий Дмитриевич"}]}]}]}