{"delo": {"name": "Право-троцкистский блок (списки осужденных)", "num": "9-Л/8-7"}, "pages": [{"image": "v07/17-171-415-117.jpg"}, {"image": "v07/17-171-415-118.jpg"}, {"image": "v07/17-171-415-119.jpg"}, {"image": "v07/17-171-415-120.jpg"}, {"image": "v07/17-171-415-121.jpg"}, {"image": "v07/17-171-415-122.jpg"}, {"image": "v07/17-171-415-123.jpg"}, {"image": "v07/17-171-415-124.jpg"}, {"image": "v07/17-171-415-125.jpg"}, {"image": "v07/17-171-415-126.jpg"}, {"image": "v07/17-171-415-127.jpg"}, {"image": "v07/17-171-415-128.jpg"}, {"image": "v07/17-171-415-129.jpg"}, {"image": "v07/17-171-415-130.jpg"}, {"image": "v07/17-171-415-131.jpg"}, {"image": "v07/17-171-415-132.jpg"}, {"image": "v07/17-171-415-133.jpg"}, {"image": "v07/17-171-415-134.jpg"}, {"image": "v07/17-171-415-135.jpg"}, {"image": "v07/17-171-415-136.jpg"}, {"image": "v07/17-171-415-137.jpg"}], "sublists": [{"title": "Украинская ССР", "persons": [{"num": "1", "name": "АГАБЕКОВ Владимир Александрович"}, {"num": "2", "name": "АЛЕКСАНДРОВ Степан Александрович"}, {"num": "3", "name": "БУДЯНСКИЙ Зиновий Адольфович"}, {"num": "4", "name": "ВЕРХОВИНЕЦ-КОСТЕВ Василий Николаевич"}, {"num": "5", "name": "ЗАТОНСКИЙ Владимир Петрович"}, {"num": "6", "name": "ЗИЛИТ Эрнст Карлович"}, {"num": "7", "name": "ИВАНОВ Павел Павлович"}, {"num": "8", "name": "КАТАЕВ Алексей Миронович"}, {"num": "9", "name": "КОБЛЕНЦ Абрам Анатольевич"}, {"num": "10", "name": "КОРСУНСКИЙ Яков Григорьевич"}, {"num": "11", "name": "КОСТЮЧЕНКО Евгений Иванович"}, {"num": "12", "name": "КОТЛЯР Борис Юрьевич"}, {"num": "13", "name": "МЕЖИКОВСКИЙ Лейб Дувидович"}, {"num": "14", "name": "МИРОНОВСКИЙ Иван Степанович"}, {"num": "15", "name": "МОЙСЕЕВ Михаил Маркович"}, {"num": "16", "name": "РОЗЕНБЕРГ Анна Яковлевна"}, {"num": "17", "name": "СИДЕРСКИЙ Зиновий Осипович"}, {"num": "18", "name": "СОКОЛОВСКИЙ Александр Александрович"}, {"num": "19", "name": "ТАМАРИН Исаак Борисович"}, {"num": "20", "name": "ФЕРРЕ-ТРУТОВСКАЯ Мария Александровна"}, {"num": "21", "name": "ХАРИ Илья Георгиевич"}, {"num": "1", "name": "АВДЕЕВ Мойсей Мойсеевич"}, {"num": "2", "name": "АЛИМОВ Павел Герасимович"}, {"num": "3", "name": "АФАНАСЬЕВ Алексей Михайлович"}, {"num": "4", "name": "БАРКОВСКИЙ Владислав Юлианович"}, {"num": "5", "name": "БЕНДЕЦКИЙ Петр Григорьевич"}, {"num": "6", "name": "БЕСОВ Дмитрий Иванович"}, {"num": "7", "name": "БЛИНДЕР Наум Соломонович"}, {"num": "8", "name": "БОРЩ Петр Федорович"}, {"num": "9", "name": "БОЧКОВ Константин Иванович"}, {"num": "10", "name": "БРАЧКО Петр Петрович"}, {"num": "11", "name": "БУДНИКОВ Петр Александрович"}, {"num": "12", "name": "ВАВИЛИН Сергей Иванович"}, {"num": "13", "name": "ВАЛЬМАН Роман Аронович"}, {"num": "14", "name": "ВАЙНШТЕЙН Яков Григорьевич"}, {"num": "15", "name": "ВИШНЕВ Михаил Алексеевич"}, {"num": "16", "name": "ГАГИН Максим Порфирьевич"}, {"num": "17", "name": "ГАРЬКАВЦЕВ Александр Акимович"}, {"num": "18", "name": "ГЕЙМАН Михаил Исидорович"}, {"num": "19", "name": "ГРИЦЕНКО Даниил Афанасьевич"}, {"num": "20", "name": "ДМИТРЕНКО Константин Гордеевич"}, {"num": "21", "name": "ДОБРОВОЛЬСКИЙ Василий Михайлович"}, {"num": "22", "name": "ДУБИНСКИЙ Марк Вениаминович"}, {"num": "23", "name": "ДУНАЕВСКИЙ Оскар Давыдович"}, {"num": "24", "name": "ЖАЛДАК Павел Яковлевич"}, {"num": "25", "name": "ЖДАНОВ Всеволод Иванович"}, {"num": "1", "name": "ЖУКОВ Андрей Васильевич"}, {"num": "2", "name": "ЗАГОРУЙ Даниил Иванович"}, {"num": "3", "name": "ЗЛОТНИЦКИЙ Дмитрий Сигизмундович"}, {"num": "4", "name": "ИВАНЧЕНКО Григорий Кириллович"}, {"num": "5", "name": "КАГАНОВИЧ Лев Харитонович"}, {"num": "6", "name": "КАЮДА Константин Калинович"}, {"num": "7", "name": "КИПЕР Макс Наумович"}, {"num": "8", "name": "КОСОБРЮХОВ-ЛЕНСКИЙ Сергей Васильевич"}, {"num": "9", "name": "КРИКЕНТ Эдмунд Карлович"}, {"num": "10", "name": "КРЯНИН Евгений Сергеевич"}, {"num": "11", "name": "КУЛИК Трофим Федорович"}, {"num": "12", "name": "КУЩЕНКО Андрей Ильич"}, {"num": "13", "name": "ЛАДА Юлиан Станиславович"}, {"num": "14", "name": "ЛАНДО Абрам Ильич"}, {"num": "15", "name": "ЛЕВЕНСОН Николай Иванович"}, {"num": "16", "name": "ЛЕШЕР Вацлав Христианович"}, {"num": "17", "name": "МАЙЛИС Герц Иезекилевич"}, {"num": "18", "name": "МАНАЕНКОВ Иосиф Петрович"}, {"num": "19", "name": "МАНЖЕЛЕЙ Иван Иванович"}, {"num": "20", "name": "МАРКИН Василий Петрович"}, {"num": "21", "name": "МЕНИКСАР Карл Георгиевич"}, {"num": "22", "name": "МЕНИКСАР Эрнст-Макс Георгиевич"}, {"num": "23", "name": "МИХАЙЛОВ Владимир Константинович"}, {"num": "24", "name": "МОСКОВЕЦ Владимир Михайлович"}, {"num": "25", "name": "НЕМИРОВСКИЙ Маркус Абрамович"}, {"num": "26", "name": "ПАВЛОВ Николай Никитович"}, {"num": "27", "name": "ПИПЕР Франц Генрихович"}, {"num": "1", "name": "ПОЛИЩУК Алексей Федорович"}, {"num": "2", "name": "ПОЛОНСКИЙ Глеб Александрович"}, {"num": "3", "name": "ПОПЛАВСКИЙ Федор Петрович"}, {"num": "4", "name": "ПОТЯГАЙЛО Соломон Владимирович"}, {"num": "5", "name": "ПОЯРКОВ Павел Михайлович"}, {"num": "6", "name": "РАППОПОРТ Григорий Исаакович"}, {"num": "7", "name": "РАБОВСКИЙ Владимир Иванович"}, {"num": "8", "name": "РАК Георгий Викторович"}, {"num": "9", "name": "РЕШЕТНЯК Аркадий Моисеевич"}, {"num": "10", "name": "РУБАНОВИЧ Леонтий Исаакович"}, {"num": "11", "name": "РОЗЕНБЕРГ Ефим Иосифович"}, {"num": "12", "name": "САЗОНОВ Михаил Львович"}, {"num": "13", "name": "СЕСКУТОВ Андрей Александрович"}, {"num": "14", "name": "СЫСУЕВ Вадим Петрович"}, {"num": "15", "name": "СМОРОДИН Михаил Антонович"}, {"num": "16", "name": "СОКОЛЕНКО Иван Тихонович"}, {"num": "17", "name": "СОКОЛОВ Николай Евгеньевич"}, {"num": "18", "name": "СОРОКИН Николай Александрович"}, {"num": "19", "name": "СТЕЦЕНКО Александр Васильевич"}, {"num": "20", "name": "ТИМОШЕНКО Карл Аверианович"}, {"num": "21", "name": "ТИССЕН Иван Иванович"}, {"num": "22", "name": "ТЫЩЕНКО Аггей Павлович"}, {"num": "23", "name": "ТОМАШЕВСКИЙ Григорий Мефодиевич"}, {"num": "24", "name": "ТОПЧИЙ Емельян Сидорович"}, {"num": "25", "name": "ТРОЙБ Григорий Моисеевич"}, {"num": "26", "name": "УМАНЦЕВ Григорий Григорьевич"}, {"num": "27", "name": "ФРЕНКЕЛЬ Александр Михайлович"}, {"num": "1", "name": "ХОЛИН Владимир Филиппович"}, {"num": "2", "name": "ХУРГИН Михаил Соломонович"}, {"num": "3", "name": "ЧИРКОВ Сергей Федорович"}, {"num": "4", "name": "ШАХОВ Александр Дмитриевич"}, {"num": "5", "name": "ШМИДТ Вильгельм Эмильевич"}, {"num": "6", "name": "АЛЕКСЕЕВ Иван Автономович"}, {"num": "7", "name": "АРТЕМЮК Михаил Иосифович"}, {"num": "8", "name": "БЕЛЯЕВ Анатолий Григорьевич"}, {"num": "9", "name": "БЫКОВ Михаил Владимирович"}, {"num": "10", "name": "БУЛГАКОВ Сергей Иванович"}, {"num": "11", "name": "ВОИН Мирон Яковлевич"}, {"num": "12", "name": "ВОЛОШИН Всеволод Константинович"}, {"num": "13", "name": "КОЗЛОВ Михаил Мойсеевич"}, {"num": "14", "name": "КОРЕНЕВ Николай Ильич"}, {"num": "15", "name": "КОРОТЕНКО Ефим Максимович"}, {"num": "16", "name": "МАЛИЧЕНКО Семен Иванович"}, {"num": "17", "name": "МИЩЕНКО Степан Васильевич"}, {"num": "18", "name": "РОЖИЦКИЙ Владимир Ионович"}, {"num": "19", "name": "СОРОКОЛАТ Григорий Андреевич"}, {"num": "20", "name": "ТРИГУБ Григорий Григорьевич"}, {"num": "21", "name": "ТРИГУБ Иван Антонович"}, {"num": "22", "name": "ФАНИН Степан Сергеевич"}, {"num": "23", "name": "ШАБРАНСКИЙ Леонид Карлович"}, {"num": "24", "name": "ЯРОСЛАВСКИЙ Иван Исидорович"}, {"num": "1", "name": "СОЛЕЦКИЙ Станислав Степанович"}, {"num": "2", "name": "АВАНЕСОВ Григорий Макарович"}, {"num": "3", "name": "БОДНЯ-БОДНЕНКО Андрей Саввич"}, {"num": "4", "name": "БОЛЬШУНОВ Семен Павлович"}, {"num": "5", "name": "БУЗАНОВ Николай Владимирович"}, {"num": "6", "name": "ГАЛЬПЕРИН Маркус Волькович"}, {"num": "7", "name": "ДЕМЧЕНКО Кузьма Иванович"}, {"num": "8", "name": "ДРУЖИНИН Иван Васильевич"}, {"num": "9", "name": "ИВАНЦОВ Алексей Иванович"}, {"num": "10", "name": "КЛЕЙМАН-ФИШЕЛЬЗОН Хаим Мошкович"}, {"num": "11", "name": "ЛИВШИЦ Лазарь Ефимович"}, {"num": "12", "name": "ЛИТВИНОВ Андрей Андреевич"}, {"num": "13", "name": "МИЛЬМАН Моисей Израилевич"}, {"num": "14", "name": "ОСЛИНГЕР Семен Израилевич"}, {"num": "15", "name": "РАГУЦКИЙ Андрей Федорович"}, {"num": "16", "name": "РАЧИНСКИЙ Василий Порфирьевич"}, {"num": "17", "name": "РЕВА Исидор Андреевич"}, {"num": "18", "name": "ТОКАРСКИЙ Матвей Борисович"}, {"num": "19", "name": "ТУНКЕЛЬРОЙТ Мордух Бенционович"}, {"num": "1", "name": "БОГДАН Павел Георгиевич"}, {"num": "2", "name": "ВОЛЬФОВСКИЙ Исаак Наумович"}, {"num": "3", "name": "ПОЛЯНЦЕВ Алексей Матвеевич"}, {"num": "4", "name": "СЕРДЮК Радион Васильевич"}, {"num": "5", "name": "ЦЕХМЕЙСТЕР Карп Николаевич"}, {"num": "6", "name": "АЙЗЕНШТОК Михаил Борисович"}, {"num": "7", "name": "ВАСИЛЬЕВ Константин Александрович"}, {"num": "8", "name": "ВАСЬКО Иван Петрович"}, {"num": "9", "name": "ВЕТЛИЦКИЙ Борис Александрович"}, {"num": "10", "name": "ВИСЛЯНСКИЙ Василий Григорьевич"}, {"num": "11", "name": "ВЛАСОВИЧ Антон Васильевич"}, {"num": "12", "name": "ВОЛЫНЦЕВ Николай Иванович"}, {"num": "13", "name": "ВОЛОСКОВЕЦ Леонид Лукич"}, {"num": "14", "name": "ГОЛЬДШТЕЙН Самсон Гершевич"}, {"num": "15", "name": "ГОМОРА Семен Ефимович"}, {"num": "16", "name": "ДЕРИНГ Василий Иванович"}, {"num": "17", "name": "ДОБРОМЫЛЬСКИЙ Михаил Иванович"}, {"num": "18", "name": "ДОГАЕВ Иван Григорьевич"}, {"num": "19", "name": "ДЬЯКОНОВ Алексей Андреевич"}, {"num": "20", "name": "ЕВСЕЕВ Тимофей Павлович"}, {"num": "1", "name": "ЕЛЕНЕВСКИЙ Николай Николаевич"}, {"num": "2", "name": "ЖАРКОВ Андрей Трофимович"}, {"num": "3", "name": "ИСААКЬЯН Мкртич Аристакесович"}, {"num": "4", "name": "КОЛЕСНИКОВ Николай Митрофанович"}, {"num": "5", "name": "КОРАБЕЛЬНИК Арон Моисеевич"}, {"num": "6", "name": "КРАСОЗОВ Василий Михайлович"}, {"num": "7", "name": "КУЗЬМИН Михаил Федорович"}, {"num": "8", "name": "ЛИХОТА Антон Афанасьевич"}, {"num": "9", "name": "ЛЮБИМСКИЙ Яков Абрамович"}, {"num": "10", "name": "МОНАСТЫРЕВ Василий Иванович"}, {"num": "11", "name": "ОСТРИН Александр Ефимович"}, {"num": "12", "name": "ОХРИМЕНКО Афанасий Ильич"}, {"num": "13", "name": "РАЕНКО Афанасий Павлович"}, {"num": "14", "name": "РОВЕНСКИЙ Михаил Абрамович"}, {"num": "15", "name": "САНГУРСКИЙ Леопольд Владимирович"}, {"num": "16", "name": "СВЕТЛИЧНЫЙ Леонид Степанович"}, {"num": "17", "name": "СУКАЧЕВ Иван Федорович"}, {"num": "18", "name": "ТИТАРЕНКО Василий Митрофанович"}, {"num": "19", "name": "ХАЛЯВА Семен Алексеевич"}, {"num": "20", "name": "ЦИНОБЕР Иосиф Аронович"}, {"num": "21", "name": "ЧЕТВЕРИКОВ Вячеслав Иванович"}, {"num": "22", "name": "ШАТОЛА Иван Иосифович"}, {"num": "23", "name": "ЗАЙЦЕВ Павел Ефремович"}, {"num": "24", "name": "ИВАНИЦКИЙ Юрий Михайлович"}, {"num": "1", "name": "КИСЛЕНКО Николай Фомич"}, {"num": "2", "name": "ЛИТВИНОВ Михаил Михайлович"}, {"num": "3", "name": "ЛЯСКАЛО Георгий Федорович"}, {"num": "4", "name": "МАРГОЛИН Даниил Евсеевич"}, {"num": "5", "name": "МОХОВ Дмитрий Иванович"}, {"num": "6", "name": "РОДКЕВИЧ Георгий Всеволодович"}, {"num": "7", "name": "СЕДОВ Иван Иванович"}, {"num": "8", "name": "СТЕФАНОВИЧ Сергей Григорьевич"}, {"num": "9", "name": "СТРЕЛЬЦОВ Александр Иванович"}, {"num": "10", "name": "АЗОС Григорий Иосифович"}, {"num": "11", "name": "АЛЯМУЖНЫЙ Авксентий Артемович"}, {"num": "12", "name": "БЕРЕЛЯ Антон Федорович"}, {"num": "13", "name": "БЕРШОВ Виктор Степанович"}, {"num": "14", "name": "ГАЙДАК-ЛОГОВ Константин Матвеевич"}, {"num": "15", "name": "ГУТОРКО Иван Васильевич"}, {"num": "16", "name": "ДУКЛЕР Моисей Давидович"}, {"num": "17", "name": "КОЛЕЖУК Николай Титович"}, {"num": "18", "name": "КРАСНОДЕД Василий Петрович"}, {"num": "19", "name": "КУЛЕШ Александр Филиппович"}, {"num": "20", "name": "ПАРАСЮК Александр Степанович"}, {"num": "21", "name": "ПОЛЕЩУК Иван Леонтьевич"}, {"num": "22", "name": "ПРОЦЕНКО Владимир Федорович"}, {"num": "1", "name": "САПИН Сергей Михайлович"}, {"num": "2", "name": "СМИРНОВ Михаил Тихонович"}, {"num": "3", "name": "ШВАРЦМАН Аврам Израилевич"}, {"num": "4", "name": "ШЕСТАК Кирилл Гаврилович"}, {"num": "5", "name": "ШУЛЬМАН Леонид Ильич"}, {"num": "6", "name": "ВЕКСЛЕР Иосиф Наумович"}, {"num": "7", "name": "ВЕНДРОВ Юлий Михайлович"}, {"num": "8", "name": "ЗИЛЬБЕРФАРБ Моисей Филиппович"}, {"num": "9", "name": "ЛОСИЦА Иван Филимонович"}, {"num": "10", "name": "ЛУКАНОВ Константин Ильич"}, {"num": "11", "name": "МЮЙР Николай Иванович"}, {"num": "12", "name": "ПШИЕВСКИЙ Михаил Исаевич"}, {"num": "13", "name": "СОКОЛОВСКИЙ Александр Владимирович"}, {"num": "14", "name": "СТОЛБУН Онуфрий Титович"}, {"num": "15", "name": "СУСЛИКОВ Даниил Максимович"}, {"num": "16", "name": "ФОРТУЯНОВ Иван Андреевич"}, {"num": "17", "name": "ХЛЕВНИКОВ Григорий Иосифович"}, {"num": "18", "name": "ШАЙКИН Александр Михайлович"}, {"num": "1", "name": "ВЕРБЕР Эрнст Меерович"}, {"num": "1", "name": "ГОРГУЦА Василий Денисович"}, {"num": "2", "name": "ДУБИЛЕР Исаак Абрамович"}, {"num": "3", "name": "МАРКМАН Хаим Абрамович"}, {"num": "4", "name": "МИХЕЛЬСОН Александр Борисович"}, {"num": "5", "name": "ТРОЦЕВСКИЙ Михаил Николаевич"}, {"num": "6", "name": "БРОНШТЕЙН Сима Пейсахович"}, {"num": "7", "name": "НАКОНЕЧНЫЙ Филипп Кондратьевич"}, {"num": "8", "name": "ДЕМИН Алексей Дмитриевич"}, {"num": "9", "name": "МОЗГОВЕНКО Николай Иванович"}, {"num": "10", "name": "ШИФРИН Аркадий Григорьевич"}, {"num": "1", "name": "МАНДЕЛЬ Яков Генрихович"}, {"num": "2", "name": "МИЛЬШТЕЙН Исроиль-Лейб Шмулевич"}, {"num": "3", "name": "ЗИМА Виктор Иванович"}, {"num": "4", "name": "ЧЕРКАШИН Николай Павлович"}, {"num": "5", "name": "ГОНЧАРОВ Семен Кузьмич"}, {"num": "6", "name": "МИРО Иван Алексеевич"}, {"num": "7", "name": "НЕНЮХИН Трофим Илларионович"}, {"num": "8", "name": "СОРЕЛЬ Илья Исаакович"}, {"num": "9", "name": "АБРОСКИН Семен Трофимович"}, {"num": "10", "name": "АРТЕМЕНКО Касьян Потапович"}, {"num": "11", "name": "БЕРЕЖНОЙ Юрий Маркианович"}, {"num": "12", "name": "БОДНЯ Михаил Емельянович"}, {"num": "13", "name": "БОЙЦОВ Иван Степанович"}, {"num": "14", "name": "БОТВИНСКИЙ Яков Абрамович"}, {"num": "15", "name": "ВОЙТЕНКО Иван Васильевич"}, {"num": "16", "name": "ГУСЕВ Сергей Иванович"}, {"num": "1", "name": "ДАНИЛЬЧЕНКО Никита Гурьевич"}, {"num": "2", "name": "ДРОБЯЗКО Иван Прокофьевич"}, {"num": "3", "name": "ЗАГОРСКИЙ Иван Константинович"}, {"num": "4", "name": "ЗНОВА Григорий Филиппович"}, {"num": "5", "name": "ЗОТОВ Георгий Николаевич"}, {"num": "6", "name": "ЗУБЕНКО Алексей Данилович"}, {"num": "7", "name": "ИСАЕВ Денис Илларионович"}, {"num": "8", "name": "КИРСАНОВ Павел Иванович"}, {"num": "9", "name": "МЕЛАМУД Самуил Израилевич"}, {"num": "10", "name": "МОГИЛА Григорий Петрович"}, {"num": "11", "name": "ПАНЧЕНКО Терентий Андреевич"}, {"num": "12", "name": "ПРОХОРОВ Александр Федорович"}, {"num": "13", "name": "РОЗИНСКИЙ Яков Ильич"}, {"num": "14", "name": "РУБАН Александр Яковлевич"}, {"num": "15", "name": "СЛУЦКИЙ Федор Лазаревич"}, {"num": "16", "name": "УРИХ Виктор Викентьевич"}, {"num": "17", "name": "ЦЫГАНКОВ Григорий Васильевич"}]}, {"title": "г.Днепропетровск-Сталинская ж.д.", "persons": [{"num": "1", "name": "АГИНСКИЙ Калман Соломонович"}, {"num": "2", "name": "АКИМЕНКО Сергей Александрович"}, {"num": "3", "name": "АКИМОВ Орест Афанасьевич"}, {"num": "4", "name": "АЛФЕРОВ Сергей Васильевич"}, {"num": "5", "name": "АМЕЛИН Павел Иванович"}, {"num": "6", "name": "АНТОНОВ-СМУЛЬСКИЙ Николай Николаевич"}, {"num": "7", "name": "АФАНАСЕНКО Тимофей Ефимович"}, {"num": "8", "name": "БЕЛЯВСКИЙ Генрих Львович"}, {"num": "9", "name": "БЛОХИН Сергей Дмитриевич"}, {"num": "10", "name": "БОЧАРОВ Владимир Григорьевич"}, {"num": "11", "name": "ВАРДО Болеслав Иванович"}, {"num": "12", "name": "ВАСИЛЬЕВ Александр Антонович"}, {"num": "13", "name": "ВДОВИЧЕНКО Яков Васильевич"}, {"num": "14", "name": "ВЕЛИКИЙ Петр Федулович"}, {"num": "15", "name": "ВЕЛИЧКЕВИЧ Виктор Сильвестрович"}, {"num": "16", "name": "ВОЛКОВ Александр Денисович"}, {"num": "17", "name": "ВОЛОЩУК Иван Гаврилович"}, {"num": "18", "name": "ГАЛАГАН Антон Иванович"}, {"num": "19", "name": "ГОЛУБИН Василий Николаевич"}, {"num": "20", "name": "ГРАЧЕВ Алексей Васильевич"}, {"num": "21", "name": "ГРИГОРЬЕВ Сергей Петрович"}, {"num": "22", "name": "ГРУШКО-МЕЛАМЕД Владимир Семенович"}, {"num": "1", "name": "ГУДКОВ Иван Андреевич"}, {"num": "2", "name": "ДАНИЛОВИЧ Моисей Давидович"}, {"num": "3", "name": "ДОЛОБКО Николай Григорьевич"}, {"num": "4", "name": "ДОМАНСКИЙ Максим Ильич"}, {"num": "5", "name": "ДУДНИК Сергей Антонович"}, {"num": "6", "name": "ДУМАНСКИЙ Андрей Андреевич"}, {"num": "7", "name": "ЕМЕЦ Максим Кузьмич"}, {"num": "8", "name": "ЕРЕМЕНКО Иван Ефимович"}, {"num": "9", "name": "ЖУРАВЛЕВ Николай Петрович"}, {"num": "10", "name": "ЗЕЛЕНОВ Александр Михайлович"}, {"num": "11", "name": "КАНТУР Григорий Минович"}, {"num": "12", "name": "КИРИЧЕНКО Иван Тимофеевич"}, {"num": "13", "name": "КИСЕЛЬ Иван Иванович"}, {"num": "14", "name": "КИССИН Борис Михайлович"}, {"num": "15", "name": "КЛИМОВИЧ Григорий Тимофеевич"}, {"num": "16", "name": "КЛОЧКО Антон Юрьевич"}, {"num": "17", "name": "КРЫЖАНОВСКИЙ Николай Климентьевич"}, {"num": "18", "name": "КУЛАЧЕНКО Иван Григорьевич"}, {"num": "19", "name": "КУРОПАТОВ Григорий Ильич"}, {"num": "20", "name": "ЛАКС Ян Карлович"}, {"num": "21", "name": "ЛЕВЧЕНКО Федор Андреевич"}, {"num": "22", "name": "МАКСИМОВ Валерий Алексеевич"}, {"num": "23", "name": "МАРТЕМЬЯНОВ Серафим Иванович"}, {"num": "24", "name": "МАСАЛЬСКИЙ Антон Нестерович"}, {"num": "25", "name": "МАТИССОН Николай Иванович"}, {"num": "26", "name": "МЕЛЬНИЧУК Борис Михайлович"}, {"num": "1", "name": "МИТКАЛЕВ Василий Александрович"}, {"num": "2", "name": "МОИСЕЕВ Ефим Моисеевич"}, {"num": "3", "name": "МУРАТОВ Семен Иванович"}, {"num": "4", "name": "НОВОХАТЬКО Тимофей Наумович"}, {"num": "5", "name": "ПЕЙЗНЕР Людвиг Иосифович"}, {"num": "6", "name": "ПЕРЕПЕЛИЦА Василий Андреевич"}, {"num": "7", "name": "ПИВОВАРОВ Иустин Исаакович"}, {"num": "8", "name": "ПЛЮЩ Федор Федосеевич"}, {"num": "9", "name": "ПОКОРА Григорий Иванович"}, {"num": "10", "name": "ПРОМЫШЛЯНСКИЙ Михаил Маркович"}, {"num": "11", "name": "РАССОХИН Павел Иванович"}, {"num": "12", "name": "РОМЕНСКИЙ Иван Матвеевич"}, {"num": "13", "name": "САРАТОВСКИЙ Вячеслав Васильевич"}, {"num": "14", "name": "СТРУЧКОВ Константин Иванович"}, {"num": "15", "name": "СУЩЕНКО Федот (Федор) Васильевич"}, {"num": "16", "name": "ТРЕСТЕР Фриц Фридрихович"}, {"num": "17", "name": "ТРИФОНОВ Николай Васильевич"}, {"num": "18", "name": "ТЮХИН Петр Григорьевич"}, {"num": "19", "name": "УЛЬЯНОВ Петр Павлович"}, {"num": "20", "name": "ЧЕЛОМБИТЬКО Алексей Федорович"}, {"num": "21", "name": "ЧЕРВЯКОВ Иван Маркелович"}, {"num": "22", "name": "ШАТОХИН Ефим Макарович"}, {"num": "23", "name": "ЯКУЩЕНКО Петр Ефимович"}, {"num": "1", "name": "БЕСТАЛАННЫЙ Харитон Федорович"}, {"num": "2", "name": "ВАССЕРАК Иван Яковлевич"}, {"num": "3", "name": "ИВАНОВ Матвей Васильевич"}, {"num": "4", "name": "КОМЕНДАНТОВ Дмитрий Васильевич"}, {"num": "5", "name": "ПАВЛЮЧЕНКО Николай Петрович"}, {"num": "6", "name": "РУДЬ Александр Ильич"}, {"num": "7", "name": "УСТЕНКО Григорий Евмениевич"}]}]}