{"title": "РГАСПИ, ф.17, оп.171, дело 9-Л/8-8", "delo": {"name": "Право-троцкистский блок (списки осужденных)", "num": "9-Л/8-8"}, "pages": [{"image": "v08/17-171-416-210.jpg"}, {"image": "v08/17-171-416-211.jpg"}, {"image": "v08/17-171-416-212.jpg"}, {"image": "v08/17-171-416-213.jpg"}, {"image": "v08/17-171-416-214.jpg"}, {"image": "v08/17-171-416-215.jpg"}, {"image": "v08/17-171-416-216.jpg"}], "sublists": [{"title": "Список от 19 апреля 1938г. [Белорусская ССР]", "sublisttitle": "Белорусская ССР", "pages": [{"page": {"pageid": "2465", "tom": "8", "pageintom": "212", "alistid": "314", "pagekind": "1", "arowcount": "24", "picturefile": "17-171-416-212.jpg", "textfile": "", "sublisttitle": "1", "categorytitle": "1", "grouptitle": "0", "podpnkvd": "0", "pometa": "0"}, "page_image": "v08/17-171-416-212.jpg", "persons": [{"num": "1", "name": "АНОШКИН Антон Андрианович"}, {"num": "2", "name": "АНТОНОВ Петр Иосифович"}, {"num": "3", "name": "БЕЛЯКОВ Николай Алексеевич"}, {"num": "4", "name": "БИРУЛЯ Антон Антонович"}, {"num": "5", "name": "БОДОПРОСТ Антон Никифорович"}, {"num": "6", "name": "ВОЛКОВ Иван Гаврилович"}, {"num": "7", "name": "ГОЛОДНЫЙ Иван Никитович"}, {"num": "8", "name": "ГОРЧАКОВ Николай Михайлович"}, {"num": "9", "name": "ГРОССБЕРГ Рихард Карлович"}, {"num": "10", "name": "ДРОЗДОВ Николай Иванович"}, {"num": "11", "name": "ЗАХАРОВ Михаил Федорович"}, {"num": "12", "name": "КАРКЛИН Павел Иванович"}, {"num": "13", "name": "КАТОЛУПОВ Петр Маркович"}, {"num": "14", "name": "КРЕЙЕР Николай Карлович"}, {"num": "15", "name": "ЛЕЙМАН Арвид Петрович"}, {"num": "16", "name": "ЛИСОВСКИЙ Станислав Игнатьевич"}, {"num": "17", "name": "МАЦЕХА Израиль Самойлович"}, {"num": "18", "name": "МЕНДЖЕРИЦКИЙ Леонид Абрамович"}, {"num": "19", "name": "МОРОЗОВ Василий Федорович"}, {"num": "20", "name": "МОРОЗОВ Петр Ильич"}, {"num": "21", "name": "НЕЙМАН Александр Георгиевич"}, {"num": "22", "name": "НИКИТЕНКО Александр Константинович"}, {"num": "23", "name": "НИКИТИН Владимир Викторович"}, {"num": "24", "name": "ПАВЛЮЧЕНКО Калистрат Иванович"}]}, {"page": {"pageid": "2466", "tom": "8", "pageintom": "213", "alistid": "314", "pagekind": "1", "arowcount": "14", "picturefile": "17-171-416-213.jpg", "textfile": "", "sublisttitle": "0", "categorytitle": "0", "grouptitle": "0", "podpnkvd": "1", "pometa": "0"}, "page_image": "v08/17-171-416-213.jpg", "persons": [{"num": "25", "name": "ПЕХОВСКИЙ Петр Иванович"}, {"num": "26", "name": "ПОВАРОВ Сергей Васильевич"}, {"num": "27", "name": "ПОЛЯК Михаил Вениаминович"}, {"num": "28", "name": "ПРИЩЕПОВ Федор Андреевич"}, {"num": "29", "name": "СТУМБУР Вольдемар Давович"}, {"num": "30", "name": "СУРКОВ Тимофей Феоктистович"}, {"num": "31", "name": "УРАЕВ Усман Мирсояфович"}, {"num": "32", "name": "ХАНИН Эмануил Михайлович"}, {"num": "33", "name": "ХАРЧИКОВ Василий Иванович"}, {"num": "34", "name": "ЧЕМИС Владислав Игнатьевич"}, {"num": "35", "name": "ШАЛИМОВ Александр Дмитриевич"}, {"num": "36", "name": "ШВАРЦ Владимир Антонович"}, {"num": "37", "name": "ШЕВЧЕНКО Иван Демьянович"}, {"num": "38", "name": "ЮВКО Владимир Кондратьевич"}]}, {"page": {"pageid": "2467", "tom": "8", "pageintom": "214", "alistid": "314", "pagekind": "1", "arowcount": "1", "picturefile": "17-171-416-214.jpg", "textfile": "", "sublisttitle": "1", "categorytitle": "1", "grouptitle": "0", "podpnkvd": "1", "pometa": "0"}, "page_image": "v08/17-171-416-214.jpg", "persons": [{"num": "1", "name": "АРОНСКИЙ Абрам Адольфович"}]}]}, {"title": "Список от 19 апреля 1938г. [Гомель-Белорусская ж.д.]", "sublisttitle": "Гомель-Белорусская ж.д.", "pages": [{"page": {"pageid": "2468", "tom": "8", "pageintom": "215", "alistid": "314", "pagekind": "1", "arowcount": "10", "picturefile": "17-171-416-215.jpg", "textfile": "", "sublisttitle": "1", "categorytitle": "1", "grouptitle": "0", "podpnkvd": "1", "pometa": "0"}, "page_image": "v08/17-171-416-215.jpg", "persons": [{"num": "1", "name": "АДАМОВ Алексей Георгиевич"}, {"num": "2", "name": "БАРКОВСКИЙ Казимир Иосифович"}, {"num": "3", "name": "ВОЛЧКОВ Алексей Петрович"}, {"num": "4", "name": "ВОРОНЕЦКИЙ Николай Иванович"}, {"num": "5", "name": "ГАЙДАШ Константин Яковлевич"}, {"num": "6", "name": "ГУПАЙЛОВИЧ Александр Васильевич"}, {"num": "7", "name": "ЖАХОВЕЦ Павел Иванович"}, {"num": "8", "name": "КАЗАКЕВИЧ Иван Фабианович"}, {"num": "9", "name": "МАНКЕВИЧ Александр Николаевич"}, {"num": "10", "name": "РАКОВ Павел Николаевич"}]}, {"page": {"pageid": "2469", "tom": "8", "pageintom": "216", "alistid": "314", "pagekind": "1", "arowcount": "4", "picturefile": "17-171-416-216.jpg", "textfile": "", "sublisttitle": "1", "categorytitle": "1", "grouptitle": "0", "podpnkvd": "1", "pometa": "0"}, "page_image": "v08/17-171-416-216.jpg", "persons": [{"num": "1", "name": "АЗБУКИН Павел Николаевич"}, {"num": "2", "name": "МАЙСАК Сергей Исидорович"}, {"num": "3", "name": "ФИЛОНОВ Сергей Филиппович"}, {"num": "4", "name": "ХАЦЬКО Николай Александрович"}]}]}]}