{"delo": {"name": "Право-троцкистский блок (списки осужденных)", "num": "9-Л/8-5"}, "pages": [{"image": "v05/17-171-413-119.jpg"}, {"image": "v05/17-171-413-120.jpg"}, {"image": "v05/17-171-413-121.jpg"}, {"image": "v05/17-171-413-122.jpg"}, {"image": "v05/17-171-413-123.jpg"}], "sublists": [{"title": "Москва-центр (выписка)", "persons": [{"num": "1", "name": "КАМИНСКИЙ Григорий Наумович"}, {"num": "2", "name": "ФИЛАТОВ Николай Алексеевич"}, {"num": "3", "name": "ГЕНКИН Ефим Борисович"}, {"num": "4", "name": "МЕЕРЗОН Жозеф Исаакович"}, {"num": "5", "name": "ХЛОПЛЯНКИН Михаил Иванович"}, {"num": "6", "name": "БОНДАРЕНКО Михаил Ильич"}, {"num": "7", "name": "ИВАНОВ Вячеслав Федорович"}, {"num": "8", "name": "АРОСЬЕВ Александр Яковлевич"}, {"num": "9", "name": "БАХУТОВ Александр Михайлович"}, {"num": "10", "name": "МЕСЯЦЕВ Павел Александрович"}, {"num": "11", "name": "ПЕТРОВСКИЙ Даниил Иванович"}, {"num": "12", "name": "ПОЛОВИНКИН Иван Матвеевич"}, {"num": "13", "name": "РЯБОВ Александр Николаевич"}, {"num": "14", "name": "ДУБОВОЙ Иван Наумович"}, {"num": "15", "name": "СЕМУШКИН Анатолий Дмитриевич"}, {"num": "16", "name": "БАРАНОВ Михаил Иванович"}, {"num": "17", "name": "БАКАУРИ Владимир Иванович"}, {"num": "18", "name": "КОВТЮХ Епифан Иович"}, {"num": "19", "name": "ЛОНГВА Роман Войцехович"}, {"num": "20", "name": "ОРЛОВ Владимир Митрофанович"}, {"num": "1", "name": "МАХОВЕР Иосиф Лазаревич"}, {"num": "2", "name": "АПРЕСОВ Гарегим Абрамович"}, {"num": "3", "name": "ХВЫЛЯ Андрей Ананьевич"}]}, {"title": "Москва-центр - список", "persons": [{"num": "1", "name": "КАМИНСКИЙ Григорий Наумович"}, {"num": "2", "name": "ПОПОВ Николай Николаевич"}, {"num": "3", "name": "СЕРЕБРОВСКИЙ Алексей Павлович"}, {"num": "4", "name": "ФИЛАТОВ Николай Алексеевич"}, {"num": "5", "name": "ГЕНКИН Ефим Борисович"}, {"num": "6", "name": "ЕРБАНОВ Михей Николаевич"}, {"num": "7", "name": "МЕЕРЗОН Жозеф Исаакович"}, {"num": "8", "name": "ХЛОПЛЯНКИН Михаил Иванович"}, {"num": "9", "name": "БОНДАРЕНКО Михаил Ильич"}, {"num": "10", "name": "ИВАНОВ Вячеслав Федорович"}, {"num": "11", "name": "РЫСКУЛОВ Тураф Рыскулович"}, {"num": "12", "name": "АРОСЬЕВ Александр Яковлевич"}, {"num": "13", "name": "БАХУТОВ Александр Михайлович"}, {"num": "14", "name": "КАУЧУКОВСКИЙ Григорий Данилович"}, {"num": "15", "name": "МЕСЯЦЕВ Павел Александрович"}, {"num": "16", "name": "ПЕТРОВСКИЙ Даниил Иванович"}, {"num": "17", "name": "ПОЛОВИНКИН Иван Матвеевич"}, {"num": "18", "name": "РЯБОВ Александр Николаевич"}, {"num": "19", "name": "СМИРНОВ Александр Петрович"}, {"num": "20", "name": "ХОДЖАНОВ Султанбек"}, {"num": "21", "name": "ДУБОВОЙ Иван Наумович"}, {"num": "22", "name": "КАГАНЕРОВА Клавдия Емельяновна"}, {"num": "23", "name": "СЕМУШКИН Анатолий Дмитриевич"}, {"num": "24", "name": "БАРАНОВ Михаил Иванович"}, {"num": "1", "name": "БАКАУРИ Владимир Иванович"}, {"num": "2", "name": "КОВТЮХ Епифан Иович"}, {"num": "3", "name": "ЛОНГВА Роман Войцехович"}, {"num": "4", "name": "ОРЛОВ Владимир Митрофанович"}, {"num": "5", "name": "БЫКИН Яков Борисович"}, {"num": "6", "name": "МУКЛЕВИЧ Ромуальд Адамович"}, {"num": "7", "name": "ГЕРЦМАН Макс Ильич"}, {"num": "8", "name": "ХВЫЛЯ Андрей Ананьевич"}, {"num": "9", "name": "РАППОПОРТ Григорий Яковлевич"}, {"num": "10", "name": "РЫНДИН Кузьма Васильевич"}, {"num": "11", "name": "КОНТОРИН Дмитрий Алексеевич"}, {"num": "12", "name": "ФОМИН Василий Кузьмич"}, {"num": "13", "name": "ОСИПОВ-ШМИДТ Осип Павлович"}, {"num": "14", "name": "МАСЛОВ Иван Николаевич"}, {"num": "15", "name": "ЛЕВИТИН Лев Маркович"}, {"num": "16", "name": "КРЮЧКОВА Екатерина Алексеевна"}, {"num": "17", "name": "РАДЧЕНКО Иван Иванович"}, {"num": "18", "name": "ЛУКЬЯНОВ Дмитрий Дмитриевич"}, {"num": "19", "name": "БЕЛОБОРОДОВ Александр Георгиевич"}]}]}